ion/__init__.py
ion/agent.py
ion/const.py
ion/core.py
ion/iris.py
ion/module.py
ion/net.py
ionai-0.98.dist-info/METADATA
ionai-0.98.dist-info/WHEEL
ionai-0.98.dist-info/top_level.txt
ionai-0.98.dist-info/RECORD
