Metadata-Version: 2.1
Name: ionai
Version: 0.98
Summary: Library for iON AI
Author: Yoshikazu NAKAJIMA
License: bmi.tmdu
